{"sections":{"banner":{"type":"collection-banner","disabled":true,"settings":{"full_width":false,"allow_transparent_header":false,"enable_parallax":true,"show_collection_title":true,"show_collection_description":false,"show_collection_image":false,"collection_title_size":"h0","image_size":"auto","mobile_text_position":"place-self-center text-center","desktop_text_position":"sm:place-self-center sm:text-center","featured_product":"","featured_product_heading":"Featured product","text_color":"#ffffff","overlay_color":"#000000","overlay_opacity":30}},"e11e3c3f-7513-459c-971e-5e93b5584109":{"type":"image-with-text-overlay","blocks":{"template--21444391371055__e11e3c3f-7513-459c-971e-5e93b5584109-heading-1":{"type":"heading","disabled":true,"settings":{"text":"Memorial Day Sale","heading_tag":"h2"}}},"block_order":["template--21444391371055__e11e3c3f-7513-459c-971e-5e93b5584109-heading-1"],"disabled":true,"settings":{"full_width":true,"allow_transparent_header":false,"enable_parallax":false,"image_size":"auto","image":"shopify:\/\/shop_images\/Sole_Deal_Days_Sale_Banner_Desktop_2025.webp","mobile_image":"shopify:\/\/shop_images\/Sole_Deal_Days_Sale_Banner_Mobile_2025.webp","mobile_text_position":"place-self-center text-center","desktop_text_position":"sm:place-self-center sm:text-center","text_color":"#ffffff","overlay_color":"#000000","overlay_opacity":0}},"featured_collection_QX9jCz":{"type":"featured-collection","settings":{"collection":"ellipticals","products":["sole-f63","sole-f65","sole-f80","sole-f85","sole-f89","sole-tt8","sole-st90"],"full_width":true,"stack_products":true,"show_progress_bar":true,"products_count":8,"products_per_row_mobile":"2","products_per_row_desktop":4,"subheading":"","title":"Treadmills for Every Workout","content":"","link_url":"","link_text":"","background":"","background_gradient":"","text_color":"","heading_color":"","heading_gradient":"linear-gradient(132deg, rgba(255, 17, 0, 1) 2%, rgba(14, 69, 138, 1) 97%)","product_card_background":"","product_card_text_color":""}},"featured_collection_YREnzt":{"type":"featured-collection","settings":{"collection":"ellipticals","products":[],"full_width":true,"stack_products":true,"show_progress_bar":true,"products_count":6,"products_per_row_mobile":"2","products_per_row_desktop":5,"subheading":"","title":"Full-body workout","content":"","link_url":"","link_text":"","background":"","background_gradient":"","text_color":"","heading_color":"","heading_gradient":"linear-gradient(132deg, rgba(255, 17, 0, 1) 2%, rgba(14, 69, 138, 1) 97%)","product_card_background":"","product_card_text_color":""}},"featured_collection_ANT33A":{"type":"featured-collection","settings":{"collection":"bikes","products":[],"full_width":true,"stack_products":true,"show_progress_bar":true,"products_count":6,"products_per_row_mobile":"2","products_per_row_desktop":3,"subheading":"","title":"Unbelievably smooth bikes. Surprisingly affordable","content":"","link_url":"","link_text":"","background":"","background_gradient":"","text_color":"","heading_color":"","heading_gradient":"linear-gradient(132deg, rgba(255, 17, 0, 1) 2%, rgba(14, 69, 138, 1) 97%)","product_card_background":"","product_card_text_color":""}},"featured_collection_CpmWRW":{"type":"featured-collection","settings":{"collection":"","products":["srvo-base","sole-srvo-complete"],"full_width":true,"stack_products":true,"show_progress_bar":false,"products_count":2,"products_per_row_mobile":"2","products_per_row_desktop":2,"subheading":"","title":"SRVO All-in-One Trainers","content":"","link_url":"","link_text":"","background":"","background_gradient":"","text_color":"","heading_color":"","heading_gradient":"linear-gradient(132deg, rgba(255, 17, 0, 1) 2%, rgba(14, 69, 138, 1) 97%)","product_card_background":"","product_card_text_color":""}},"featured_collection_qR94XH":{"type":"featured-collection","settings":{"collection":"","products":["sole-sw101","sole-sw106","sole-sw111","sole-sw121","sole-sw116","sw180-adjustable-dumbbells-80lbs"],"full_width":true,"stack_products":true,"show_progress_bar":true,"products_count":12,"products_per_row_mobile":"2","products_per_row_desktop":4,"subheading":"","title":"Get stronger at home","content":"","link_url":"","link_text":"","background":"","background_gradient":"","text_color":"","heading_color":"","heading_gradient":"linear-gradient(132deg, rgba(255, 17, 0, 1) 2%, rgba(14, 69, 138, 1) 95%)","product_card_background":"","product_card_text_color":""}},"featured_collection_H9LHA7":{"type":"featured-collection","settings":{"collection":"","products":["sole-sr550"],"full_width":true,"stack_products":false,"show_progress_bar":true,"products_count":2,"products_per_row_mobile":"2","products_per_row_desktop":4,"subheading":"","title":"Row all year long","content":"","link_url":"","link_text":"","background":"","background_gradient":"","text_color":"","heading_color":"","heading_gradient":"linear-gradient(132deg, rgba(255, 17, 0, 1) 2%, rgba(14, 69, 138, 1) 97%)","product_card_background":"","product_card_text_color":""}},"d392f384-505b-499a-99dc-00ee7f39baa6":{"type":"rich-text","blocks":{"7db6f238-2b0b-4b08-8f04-f3ec12475554":{"type":"heading","settings":{"text":"Premium Exercise Equipment at a Fraction of the Cost","heading_tag":"h1","text_color":"","gradient":"linear-gradient(85deg, rgba(255, 159, 0, 1), rgba(157, 34, 39, 1) 100%)"}},"template--21444391371055__d392f384-505b-499a-99dc-00ee7f39baa6-richtext-1":{"type":"richtext","settings":{"content":"<h6>Don't miss out on this incredible opportunity to own our best machines at their best prices ever! <\/h6><p>These machines are the last ones we have! Make the deal and get in shape! There has literally never been a better time to get fit with prices like these! <\/p>"}}},"block_order":["7db6f238-2b0b-4b08-8f04-f3ec12475554","template--21444391371055__d392f384-505b-499a-99dc-00ee7f39baa6-richtext-1"],"disabled":true,"settings":{"full_width":true,"content_width":"large","text_position":"center","background":"","background_gradient":"","text_color":""}},"db06c0b2-bd02-4a1f-8619-fd63bcd30d5e":{"type":"featured-collection","disabled":true,"settings":{"collection":"","products":["sole-sb700"],"full_width":true,"stack_products":true,"show_progress_bar":false,"products_count":3,"products_per_row_mobile":"2","products_per_row_desktop":3,"subheading":"","title":"","content":"","link_url":"","link_text":"","background":"","background_gradient":"","text_color":"","heading_color":"","heading_gradient":"","product_card_background":"","product_card_text_color":""}},"featured_product_AMyG66":{"type":"featured-product","blocks":{"vendor_HnbRfz":{"type":"vendor","disabled":true,"settings":{}},"title_B8FCwn":{"type":"title","settings":{"heading_tag":"h2"}},"badges_37HXnm":{"type":"badges","settings":{}},"price_ptcKHA":{"type":"price","settings":{"show_taxes_notice":false}},"rating_jL8CCy":{"type":"rating","settings":{"show_empty":false}},"separator_VeBYwJ":{"type":"separator","settings":{}},"description_kdPrKf":{"type":"description","settings":{"icon":"none","icon_width":20,"collapse_content":false}},"variant_picker_XyzYkq":{"type":"variant_picker","settings":{"hide_sold_out_variants":false,"stack_blocks":true,"selector_style":"block","swatch_selector_style":"swatch","variant_image_options":"","size_chart_page":""}},"quantity_selector_yHkWHR":{"type":"quantity_selector","disabled":true,"settings":{}},"buy_buttons_yQhYBf":{"type":"buy_buttons","settings":{"show_payment_button":true,"show_gift_card_recipient":true,"atc_button_background":"","atc_button_text_color":"","payment_button_background":"","payment_button_text_color":""}},"pickup_availability_KLKjnH":{"type":"pickup_availability","settings":{}}},"block_order":["vendor_HnbRfz","title_B8FCwn","badges_37HXnm","price_ptcKHA","rating_jL8CCy","separator_VeBYwJ","description_kdPrKf","variant_picker_XyzYkq","quantity_selector_yHkWHR","buy_buttons_yQhYBf","pickup_availability_KLKjnH"],"disabled":true,"settings":{"full_width":true,"product":"sole-f89","desktop_media_width":55,"desktop_media_layout":"carousel_thumbnails_bottom","mobile_media_size":"expanded","mobile_carousel_control":"free_scroll","enable_video_autoplay":true,"enable_video_looping":false,"enable_image_zoom":true,"max_image_zoom_level":3,"background":"","background_gradient":"","text_color":"","input_background":"rgba(0,0,0,0)","input_text_color":""}},"video_cDMajU":{"type":"video","blocks":{"play_yEQh9L":{"type":"play","settings":{}},"heading_beKXe3":{"type":"heading","settings":{"text":"F89: Our Highest End Treadmill","heading_tag":"h3"}}},"block_order":["play_yEQh9L","heading_beKXe3"],"disabled":true,"settings":{"full_width":true,"allow_transparent_header":false,"autoplay":false,"video_size":"auto","video":"shopify:\/\/files\/videos\/WhatDefines.30s.Hor.4K.FINAL.mov","external_video_url":"https:\/\/www.youtube.com\/watch?v=_9VUPq3SxOc","poster":"shopify:\/\/shop_images\/hero_F89_wide.webp","text_color":"#ffffff","overlay_color":"#000000","overlay_opacity":30}},"rich_text_a3CFEf":{"type":"rich-text","blocks":{"subheading_89dAig":{"type":"subheading","settings":{"text":"These Best Deals Won't Last Long, Now is the Time to Buy!"}}},"block_order":["subheading_89dAig"],"settings":{"full_width":true,"content_width":"small","text_position":"center","background":"","background_gradient":"","text_color":""}},"f22dcb8e-ce0e-4a57-8480-87b43789813f":{"type":"image-with-text-overlay","blocks":{"template--21812144177455__f22dcb8e-ce0e-4a57-8480-87b43789813f-subheading-1":{"type":"subheading","settings":{"text":"The SOLE Experience"}},"template--21812144177455__f22dcb8e-ce0e-4a57-8480-87b43789813f-heading-1":{"type":"heading","settings":{"text":"Enjoy Complimentary Curbside Shipping with Every SOLE Order!","heading_tag":"h1"}},"template--21812144177455__f22dcb8e-ce0e-4a57-8480-87b43789813f-richtext-1":{"type":"richtext","settings":{"content":"<p>Never worry about having to pay for shipping with SOLE. All our products ship for FREE with our Curbside Delivery option. <br\/><em>Restrictions Apply. See our Shipping Policies page. <\/em><\/p>"}}},"block_order":["template--21812144177455__f22dcb8e-ce0e-4a57-8480-87b43789813f-subheading-1","template--21812144177455__f22dcb8e-ce0e-4a57-8480-87b43789813f-heading-1","template--21812144177455__f22dcb8e-ce0e-4a57-8480-87b43789813f-richtext-1"],"disabled":true,"settings":{"full_width":true,"allow_transparent_header":false,"enable_parallax":true,"image_size":"sm","image":"shopify:\/\/shop_images\/Shipping.webp","mobile_text_position":"place-self-center-start text-start","desktop_text_position":"sm:place-self-center sm:text-center","text_color":"#ffffff","overlay_color":"#000000","overlay_opacity":40}},"5d36c499-7288-4ef3-bd65-a8e832ee1a0a":{"type":"rich-text","blocks":{"template--21812144177455__5d36c499-7288-4ef3-bd65-a8e832ee1a0a-heading-1":{"type":"heading","settings":{"text":"The SOLE+ Advantage","heading_tag":"h1","text_color":"","gradient":""}},"template--21812144177455__5d36c499-7288-4ef3-bd65-a8e832ee1a0a-richtext-1":{"type":"richtext","settings":{"content":"<p>We also offer FREE online fitness classes to every one of our customers.<\/p>"}}},"block_order":["template--21812144177455__5d36c499-7288-4ef3-bd65-a8e832ee1a0a-heading-1","template--21812144177455__5d36c499-7288-4ef3-bd65-a8e832ee1a0a-richtext-1"],"settings":{"full_width":true,"content_width":"medium","text_position":"center","background":"","background_gradient":"","text_color":""}},"d413c24c-5388-49ce-bb22-49bd08928945":{"type":"slideshow","blocks":{"template--21812144177455__d413c24c-5388-49ce-bb22-49bd08928945-image-1":{"type":"image","settings":{"image":"shopify:\/\/shop_images\/Banner_3.png","content_max_width":780,"mobile_text_position":"place-self-center text-center","desktop_text_position":"sm:place-self-center sm:text-center","subheading":"","title":"WITH OUR SOLE+ APP YOU CAN ACCESS THOUSANDS OF FREE WORKOUT CLASSES","heading_tag":"h2","button_text":"CHECK OUT THE BENEFITS","button_link":"shopify:\/\/pages\/sole","text_color":"#ffffff","button_background":"#ffffff","button_text_color":"#000000","overlay_color":"#000000","overlay_opacity":30,"background":"","background_gradient":""}}},"block_order":["template--21812144177455__d413c24c-5388-49ce-bb22-49bd08928945-image-1"],"settings":{"full_width":true,"allow_transparent_header":true,"show_initial_transition":false,"image_size":"auto","controls_type":"outline_arrows","transition_type":"fade_with_text","autoplay":false,"cycle_speed":6,"background":"#f2f2f2","background_gradient":""}},"main":{"type":"main-collection","disabled":true,"settings":{"products_per_page":24,"products_per_row_mobile":"2","products_per_row_desktop":4,"filter_layout":"drawer","show_sort_by":true,"show_filters":true,"show_filter_group_name":false,"show_filter_values_count":true,"open_first_filter_group":false}},"771580e6-772d-463f-aeb9-1ee20975ca7a":{"type":"faq","blocks":{"template--21812144177455__771580e6-772d-463f-aeb9-1ee20975ca7a-item-2":{"type":"item","settings":{"title":"Customer Reviews: Hear from Our Satisfied Users","content":"<p>Don't just take our word for it. Read through the experiences of countless satisfied customers who have transformed their fitness routines with our treadmills. Their stories are a testament to our commitment to quality and customer satisfaction.<\/p>"}},"template--21812144177455__771580e6-772d-463f-aeb9-1ee20975ca7a-item-3":{"type":"item","settings":{"title":"Frequently Asked Questions","content":"<p>Have questions? We've got answers. Check out our <a href=\"\/pages\/faq\" title=\"Frequently Asked Questions\">FAQ section<\/a> where we address common queries about treadmill maintenance, warranty, delivery, and more.<\/p>"}}},"block_order":["template--21812144177455__771580e6-772d-463f-aeb9-1ee20975ca7a-item-2","template--21812144177455__771580e6-772d-463f-aeb9-1ee20975ca7a-item-3"],"disabled":true,"settings":{"full_width":true,"subheading":"SOLE","title":"REVIEWS AND FAQ","content":"","team_avatar_width":160,"support_hours":"","answer_time":"","button_text":"","button_url":"","text_position":"center","background":"","background_gradient":"","text_color":"","heading_color":"","heading_gradient":"","button_background":"","button_text_color":"","accordion_background":"","accordion_text_color":""}}},"order":["banner","e11e3c3f-7513-459c-971e-5e93b5584109","featured_collection_QX9jCz","featured_collection_YREnzt","featured_collection_ANT33A","featured_collection_CpmWRW","featured_collection_qR94XH","featured_collection_H9LHA7","d392f384-505b-499a-99dc-00ee7f39baa6","db06c0b2-bd02-4a1f-8619-fd63bcd30d5e","featured_product_AMyG66","video_cDMajU","rich_text_a3CFEf","f22dcb8e-ce0e-4a57-8480-87b43789813f","5d36c499-7288-4ef3-bd65-a8e832ee1a0a","d413c24c-5388-49ce-bb22-49bd08928945","main","771580e6-772d-463f-aeb9-1ee20975ca7a"]}